{
    "Pra começar": {
        "Pães": [
            {
                "nome": "Pão de Queijo - 6 unidades",
                "preço": 12.0,
                "informação-extra": null,
                "descrição": null
            },
            {
                "nome": "Pão de Batata com Requeijão",
                "preço": 12.0,
                "informação-extra": null,
                "descrição": "Unidade"
            },
            {
                "nome": "Pão de Batata Misto",
                "preço": 12.0,
                "informação-extra": null,
                "descrição": "Unidade"
            },
            {
                "nome": "Pão na chapa",
                "preço": 10.0,
                "informação-extra": null,
                "descrição": null
            },
            {
                "nome": "Croissant",
                "preço": 12.0,
                "informação-extra": null,
                "descrição": "Recheios: Misto; Frango com catupiry; Quatro Queijos e chocolate"
            }
        ],
        "Salgados": [
            {
                "nome": "Empanada De Carne",
                "preço": 13.0,
                "informação-extra": null,
                "descrição": "Empanada recheada com carne, especiarias e azeitonas"
            },
            {
                "nome": "Empanada De Queijo Com Cebola",
                "preço": 13.0,
                "informação-extra": null,
                "descrição": "Empanada recheada com queijo e cebola caramelizada"
            },
            {
                "nome": "Coxinha",
                "preço": 12.0,
                "informação-extra": null,
                "descrição": null
            },
            {
                "nome": "Risoles de Palmito",
                "preço": 12.0,
                "informação-extra": null,
                "descrição": null
            },
            {
                "nome": "Risoles de Presunto e queijo",
                "preço": 12.0,
                "informação-extra": null,
                "descrição": null
            },
            {
                "nome": "Bolinha de Queijo",
                "preço": 12.0,
                "informação-extra": null,
                "descrição": null
            }
        ]
    },
    "Sanduiches e Batata Fritas": {
        "Sanduiches": [
            {
                "nome": "Bauru",
                "preço": 19.0,
                "informação-extra": null,
                "descrição": "Pão, presunto, queijo, tomate e oregano"
            },
            {
                "nome": "Misto Quente no Francês ou no Pão de Forma",
                "preço": 18.0,
                "informação-extra": null,
                "descrição": "Pão, presunto e queijo"
            },
            {
                "nome": "Queijo Quente no Francês ou no Pão de forma",
                "preço": 16.0,
                "informação-extra": null,
                "descrição": "Pão, american cheese e cheddar"
            },
            {
                "nome": "Batata Frita 150g",
                "preço": 18.0,
                "informação-extra": null,
                "descrição": null
            }
        ],
        "Sanduiches Especiais": [
            {
                "nome": "Caprese",
                "preço": 42.0,
                "informação-extra": null,
                "descrição": "Pão, tomate, muçarela de búfala e manjericão"
            },
            {
                "nome": "Sanduiche de Frango",
                "preço": 42.0,
                "informação-extra": null,
                "descrição": "Pão, alface, pedaços de frango grelhado, tomate, cebola, maionese da casa e molho Cepêra Mostarda e Mel"
            },
            {
                "nome": "Sanduiche Mediterrâneo",
                "preço": 46.0,
                "informação-extra": null,
                "descrição": "Pão, azeite, rúcula, presunto cru, tomate cereja, muçarela de Búfala e azeitonas pretas"
            }
        ]
    },
    "Refeições": {
        "Tortas ": [
            {
                "nome": "Torta de Camarão (Fatia)",
                "preço": 34.0,
                "informação-extra": null,
                "descrição": "Complete sua torta, adicionando uma mini salada do dia no valor promocional de R$15,00"
            },
            {
                "nome": "Torta de Frango (Fatia)",
                "preço": 30.0,
                "informação-extra": null,
                "descrição": "Complete sua torta, adicionando uma mini salada do dia no valor promocional de R$15,00"
            },
            {
                "nome": "Torta de Palmito (Fatia)",
                "preço": 30.0,
                "informação-extra": null,
                "descrição": "Complete sua torta, adicionando uma mini salada do dia no valor promocional de R$15,00"
            },
            {
                "nome": "Torta de Legumes (Fatia)",
                "preço": 25.0,
                "informação-extra": null,
                "descrição": "Complete sua torta, adicionando uma mini salada do dia no valor promocional de R$15,00"
            }
        ],
        "Saladas": [
            {
                "nome": "Salada do Dia",
                "preço": 25.0,
                "informação-extra": null,
                "descrição": null
            },
            {
                "nome": "Salada Verde",
                "preço": 38.0,
                "informação-extra": null,
                "descrição": "Mix de folhas verdes"
            },
            {
                "nome": "Salada Caprese",
                "preço": 42.0,
                "informação-extra": null,
                "descrição": null
            },
            {
                "nome": "Salada Caesar",
                "preço": 45.0,
                "informação-extra": null,
                "descrição": "Alface americana, lâminas de frango grelhado, croutons e molho ceasar"
            }
        ],
        "Massas": [
            {
                "nome": "Ravioli de Muçarela",
                "preço": null,
                "informação-extra": null,
                "descrição": "Escolha o molho de sua preferência"
            },
            {
                "nome": "Tortelli de Limão Siciliano",
                "preço": null,
                "informação-extra": null,
                "descrição": "Escolha o Molho de sua preferência"
            },
            {
                "nome": "Nhoque",
                "preço": null,
                "informação-extra": null,
                "descrição": "Escolha o seu molho"
            },
            {
                "nome": "Penne",
                "preço": 52.0,
                "informação-extra": null,
                "descrição": "Escolha os molhos"
            }
        ],
        "Pratos Principais": [
            {
                "nome": "Parmegiana de Frango",
                "preço": 55.0,
                "informação-extra": null,
                "descrição": "Filet de frango a parmegiana, arroz e batatas fritas"
            },
            {
                "nome": "Strogonoff de Filet Mignon",
                "preço": 69.0,
                "informação-extra": null,
                "descrição": "Acompanha arroz e fritas"
            },
            {
                "nome": "Strogonoff de Frango",
                "preço": 59.0,
                "informação-extra": null,
                "descrição": "Acompanha arroz e fritas"
            },
            {
                "nome": "Feijoada",
                "preço": 58.0,
                "informação-extra": null,
                "descrição": "Arroz, couve, farofa, vinagrete e laranja"
            }
        ]
    },
    "Doces e Sorvetes": {
        "Açai e Sorvete": [
            {
                "nome": "Açai",
                "preço": null,
                "informação-extra": null,
                "descrição": "Pote P R$15 Pote G R$24"
            },
            {
                "nome": "Creme de Cupuaçu",
                "preço": null,
                "informação-extra": null,
                "descrição": "Pote P R$15 Pote G R$24"
            },
            {
                "nome": "Creme de Manga",
                "preço": null,
                "informação-extra": null,
                "descrição": "Pote P R$15 Pote G R$24"
            },
            {
                "nome": "Pitaya com Maracujá",
                "preço": null,
                "informação-extra": null,
                "descrição": "Pote P R$15 Pote G R$24"
            }
        ],
        "Sobremesas": [
            {
                "nome": "Eclair de pistache",
                "preço": 14.0,
                "informação-extra": null,
                "descrição": null
            },
            {
                "nome": "Bolo Fatia",
                "preço": 13.0,
                "informação-extra": null,
                "descrição": "Verifique disponibilidade de sabor"
            },
            {
                "nome": "Pão de Mel",
                "preço": 12.0,
                "informação-extra": null,
                "descrição": null
            }
        ],
        "Bomboniere": [
            {
                "nome": "Bala Fini",
                "preço": 2.0,
                "informação-extra": null,
                "descrição": null
            },
            {
                "nome": "Chiclete Trident - verificar saborea disponíveis",
                "preço": 4.0,
                "informação-extra": null,
                "descrição": null
            },
            {
                "nome": "Chiclete Mentos",
                "preço": 17.0,
                "informação-extra": null,
                "descrição": null
            },
            {
                "nome": "Kit Kat",
                "preço": 7.0,
                "informação-extra": null,
                "descrição": null
            },
            {
                "nome": "Chocolate Hershey",
                "preço": 10.0,
                "informação-extra": null,
                "descrição": null
            },
            {
                "nome": "Snickers",
                "preço": 4.0,
                "informação-extra": null,
                "descrição": null
            },
            {
                "nome": "4 Balas 7 Belo",
                "preço": 1.0,
                "informação-extra": null,
                "descrição": null
            }
        ]
    },
    "Bebidas": {
        "Café e Chocolate": [
            {
                "nome": "Expresso",
                "preço": 7.0,
                "informação-extra": null,
                "descrição": null
            },
            {
                "nome": "Expresso Duplo",
                "preço": 12.0,
                "informação-extra": null,
                "descrição": null
            },
            {
                "nome": "Cappucino",
                "preço": 14.0,
                "informação-extra": null,
                "descrição": "Expresso, leite vaporizado e cacau em pó"
            },
            {
                "nome": "Macchiato",
                "preço": 12.0,
                "informação-extra": null,
                "descrição": "Expresso e crema"
            },
            {
                "nome": "Macchiato Duplo",
                "preço": 17.0,
                "informação-extra": null,
                "descrição": "Expresso e crema"
            },
            {
                "nome": "Chocolate Quente",
                "preço": 18.0,
                "informação-extra": null,
                "descrição": "Chocolate e leite"
            }
        ],
        "Café Coado -  Chapada Diamantina": [
            {
                "nome": "Café Rigno",
                "preço": 18.0,
                "informação-extra": null,
                "descrição": "Campeão do Cup of Excellence (2022) e tetra pela BSCA e ABIC. Produzido em Piatã na Chapada da Diamantina"
            },
            {
                "nome": "Café Pai Inácio",
                "preço": 18.0,
                "informação-extra": null,
                "descrição": "Produtor premiado pela BSCA em 2023. Produzido em Piatã, Chapada Diamantina. * Temos tbm o café a venda para que leve para casa."
            },
            {
                "nome": "Café Terramater",
                "preço": 18.0,
                "informação-extra": null,
                "descrição": "Café cultivado em sistema agroflorestal, com cuidado na preservação da vegetação. Produzido em Ibicoara, Chapada Diamantina. * Temos tbm o café a venda para que leve para casa."
            },
            {
                "nome": "Café Microlote",
                "preço": 18.0,
                "informação-extra": null,
                "descrição": "Esse grão é do sitio que ficou em 7º lugar em 2022 no concurso Cup of Excellence Produzido em Piatã, Chapada Diamantina. * Temos tbm o café a venda para que leve para casa."
            }
        ],
        "Café Gelados": [
            {
                "nome": "Latte",
                "preço": 17.0,
                "informação-extra": null,
                "descrição": null
            },
            {
                "nome": "Café Latte de chocolate",
                "preço": 22.0,
                "informação-extra": null,
                "descrição": null
            },
            {
                "nome": "Café Latte de caramelo",
                "preço": 22.0,
                "informação-extra": null,
                "descrição": null
            },
            {
                "nome": "Mocha Chocolate",
                "preço": 22.0,
                "informação-extra": null,
                "descrição": "Expresso, leite, calda de chocolate, gelo e chantilly"
            },
            {
                "nome": "Mocha Caramelo",
                "preço": 22.0,
                "informação-extra": null,
                "descrição": "Expresso, leite, calda de caramelo, gelo e chantilly"
            },
            {
                "nome": "Frapuccino",
                "preço": 22.0,
                "informação-extra": null,
                "descrição": null
            },
            {
                "nome": "Expresso Tônica",
                "preço": 17.0,
                "informação-extra": null,
                "descrição": null
            },
            {
                "nome": "Chai Latte",
                "preço": 22.0,
                "informação-extra": null,
                "descrição": null
            }
        ],
        "Shakes e Smoothies": [
            {
                "nome": "Shake de Whey com chocolate",
                "preço": 22.0,
                "informação-extra": null,
                "descrição": null
            },
            {
                "nome": "Shake de Whey com Banana",
                "preço": 22.0,
                "informação-extra": null,
                "descrição": null
            },
            {
                "nome": "Smoothie de banana com Açai",
                "preço": 24.0,
                "informação-extra": null,
                "descrição": null
            }
        ],
        "Soda Italiana": [
            {
                "nome": "Maçã verde",
                "preço": 14.0,
                "informação-extra": null,
                "descrição": null
            }
        ],
        "Sucos ": [
            {
                "nome": "Rubis Refrescante",
                "preço": 16.0,
                "informação-extra": null,
                "descrição": "frutas vermelhas e xarope de açúcar"
            },
            {
                "nome": "Limonada",
                "preço": 15.0,
                "informação-extra": null,
                "descrição": null
            },
            {
                "nome": "Passionberrys",
                "preço": 17.0,
                "informação-extra": null,
                "descrição": "Frutas vermelhas, maracujá e xarope de açúcar"
            },
            {
                "nome": "Maracujá",
                "preço": 15.0,
                "informação-extra": null,
                "descrição": "maracujá e xarope de açúcar"
            },
            {
                "nome": "Laranja (natural)",
                "preço": 15.0,
                "informação-extra": null,
                "descrição": "maracujá e xarope de açúcar"
            }
        ],
        "Refrigerantes, águas e energéticos": [
            {
                "nome": "Água Sem Gás",
                "preço": 7.0,
                "informação-extra": null,
                "descrição": null
            },
            {
                "nome": "Água Com Gás",
                "preço": 7.0,
                "informação-extra": null,
                "descrição": null
            },
            {
                "nome": "Refrigerantes",
                "preço": 8.0,
                "informação-extra": null,
                "descrição": "Coca Cola Coca Cola Zero Guaraná Antartica Guaraná Antartica Zero Fanta Laranja Fanta Uva Sprite"
            },
            {
                "nome": "Red Bull",
                "preço": 14.0,
                "informação-extra": null,
                "descrição": null
            },
            {
                "nome": "Chá Mate",
                "preço": 10.0,
                "informação-extra": null,
                "descrição": "Lichia; Pêssego; Limão; Chá verde"
            },
            {
                "nome": "Suco de caixinha",
                "preço": 6.0,
                "informação-extra": null,
                "descrição": null
            },
            {
                "nome": "H2O",
                "preço": 10.0,
                "informação-extra": null,
                "descrição": "Normal ou limão"
            },
            {
                "nome": "Gatorade",
                "preço": 10.0,
                "informação-extra": null,
                "descrição": "Verifique disponibilidade de sabor"
            },
            {
                "nome": "Mupy",
                "preço": 6.0,
                "informação-extra": null,
                "descrição": "Verificar disponibilidade de sabor"
            },
            {
                "nome": "Toddynho",
                "preço": 6.5,
                "informação-extra": null,
                "descrição": null
            }
        ]
    },
    "endereço": "Rua Maranhão, 617, Higienópolis, São Paulo, SP, Brasil",
    "telefone": "(11) 91289-4551",
    "email": "ziv.gallery1@gmail.com",
    "website": "https://www.zivgallery.com/",
    "name": "Ziv Gallery Higienópolis"
}